{"responses": [{"textAnnotations": [{"locale": "ja", "description": "20447 80301443\n\u540d\u79f0\u304a\u306b\u308a\nY14\n\u30d9\u30fc\u30b3\u30f3 \u305f\u307e\u3054\n\u3048\u3054\u307e\u5165\u308a\u30d9\u30fc\u30b3\u30f3\u63d0\u304d\u3001 \u3001DH\u79c1\nA (7\n\u7b49 \u30b7\u30f3\u3001\u304f\u3093\u591c\u767a\u8272\u5229(\u78bc\u4fee Na)\n\u6750\u4e00\u90e8\u306b\u3001\u5c0f\u9ea6\u3001\u8c5a\u8089\u3092\u542b\u3080)\n\u8b70 19 96\u5348\u5f8c48\u6642\n\u4fdd\u5b58\u65b9\u6cd5\u5c04\u65e5\u5149\u53ca\u3073\u4e8b\u6e29\u3092\u907f\u3051\u3066\u4e0b\u3055\u3044\nPJ23\n0120-634058\n11 2-48\n1 2 U PA9 2kcal\n\u70ad\u6c34\u5316\u726937.4g Na 21 8g\n8g M2 68\n", "boundingPoly": {"vertices": [{"x": 192, "y": 160}, {"x": 593, "y": 160}, {"x": 593, "y": 440}, {"x": 192, "y": 440}]}}, {"description": "20447", "boundingPoly": {"vertices": [{"x": 250, "y": 160}, {"x": 284, "y": 161}, {"x": 284, "y": 179}, {"x": 250, "y": 178}]}}, {"description": "80301443", "boundingPoly": {"vertices": [{"x": 286, "y": 160}, {"x": 341, "y": 161}, {"x": 341, "y": 179}, {"x": 286, "y": 178}]}}, {"description": "\u540d\u79f0", "boundingPoly": {"vertices": [{"x": 238, "y": 174}, {"x": 272, "y": 175}, {"x": 271, "y": 196}, {"x": 237, "y": 195}]}}, {"description": "\u304a\u306b\u308a", "boundingPoly": {"vertices": [{"x": 284, "y": 179}, {"x": 351, "y": 182}, {"x": 350, "y": 200}, {"x": 283, "y": 197}]}}, {"description": "Y14", "boundingPoly": {"vertices": [{"x": 553, "y": 191}, {"x": 591, "y": 200}, {"x": 586, "y": 219}, {"x": 548, "y": 209}]}}, {"description": "\u30d9\u30fc\u30b3\u30f3", "boundingPoly": {"vertices": [{"x": 405, "y": 183}, {"x": 501, "y": 201}, {"x": 497, "y": 224}, {"x": 401, "y": 206}]}}, {"description": "\u305f\u307e\u3054", "boundingPoly": {"vertices": [{"x": 527, "y": 205}, {"x": 591, "y": 217}, {"x": 587, "y": 240}, {"x": 523, "y": 228}]}}, {"description": "\u3048\u3054\u307e", "boundingPoly": {"vertices": [{"x": 238, "y": 207}, {"x": 315, "y": 217}, {"x": 312, "y": 240}, {"x": 235, "y": 230}]}}, {"description": "\u5165\u308a", "boundingPoly": {"vertices": [{"x": 317, "y": 218}, {"x": 347, "y": 222}, {"x": 344, "y": 245}, {"x": 314, "y": 241}]}}, {"description": "\u30d9\u30fc\u30b3\u30f3", "boundingPoly": {"vertices": [{"x": 349, "y": 221}, {"x": 409, "y": 229}, {"x": 406, "y": 253}, {"x": 346, "y": 245}]}}, {"description": "\u63d0", "boundingPoly": {"vertices": [{"x": 412, "y": 230}, {"x": 430, "y": 232}, {"x": 427, "y": 255}, {"x": 409, "y": 253}]}}, {"description": "\u304d", "boundingPoly": {"vertices": [{"x": 432, "y": 233}, {"x": 442, "y": 234}, {"x": 439, "y": 257}, {"x": 429, "y": 256}]}}, {"description": "\u3001", "boundingPoly": {"vertices": [{"x": 440, "y": 249}, {"x": 442, "y": 249}, {"x": 442, "y": 250}, {"x": 440, "y": 250}]}}, {"description": "\u3001", "boundingPoly": {"vertices": [{"x": 459, "y": 239}, {"x": 494, "y": 244}, {"x": 491, "y": 264}, {"x": 456, "y": 260}]}}, {"description": "DH", "boundingPoly": {"vertices": [{"x": 507, "y": 243}, {"x": 545, "y": 248}, {"x": 542, "y": 271}, {"x": 504, "y": 266}]}}, {"description": "\u79c1", "boundingPoly": {"vertices": [{"x": 547, "y": 248}, {"x": 593, "y": 254}, {"x": 590, "y": 277}, {"x": 544, "y": 271}]}}, {"description": "A", "boundingPoly": {"vertices": [{"x": 487, "y": 261}, {"x": 500, "y": 263}, {"x": 497, "y": 285}, {"x": 484, "y": 283}]}}, {"description": "(7", "boundingPoly": {"vertices": [{"x": 529, "y": 267}, {"x": 549, "y": 270}, {"x": 546, "y": 291}, {"x": 526, "y": 289}]}}, {"description": "\u7b49", "boundingPoly": {"vertices": [{"x": 222, "y": 246}, {"x": 239, "y": 248}, {"x": 236, "y": 269}, {"x": 219, "y": 267}]}}, {"description": "\u30b7", "boundingPoly": {"vertices": [{"x": 293, "y": 262}, {"x": 315, "y": 265}, {"x": 313, "y": 278}, {"x": 291, "y": 275}]}}, {"description": "\u30f3", "boundingPoly": {"vertices": [{"x": 319, "y": 265}, {"x": 337, "y": 267}, {"x": 335, "y": 280}, {"x": 317, "y": 278}]}}, {"description": "\u3001", "boundingPoly": {"vertices": [{"x": 340, "y": 262}, {"x": 345, "y": 263}, {"x": 342, "y": 284}, {"x": 337, "y": 284}]}}, {"description": "\u304f", "boundingPoly": {"vertices": [{"x": 352, "y": 267}, {"x": 362, "y": 268}, {"x": 360, "y": 284}, {"x": 350, "y": 283}]}}, {"description": "\u3093", "boundingPoly": {"vertices": [{"x": 370, "y": 266}, {"x": 383, "y": 268}, {"x": 380, "y": 290}, {"x": 367, "y": 288}]}}, {"description": "\u591c", "boundingPoly": {"vertices": [{"x": 384, "y": 268}, {"x": 409, "y": 271}, {"x": 406, "y": 293}, {"x": 381, "y": 290}]}}, {"description": "\u767a", "boundingPoly": {"vertices": [{"x": 411, "y": 273}, {"x": 436, "y": 276}, {"x": 433, "y": 298}, {"x": 408, "y": 295}]}}, {"description": "\u8272", "boundingPoly": {"vertices": [{"x": 438, "y": 275}, {"x": 455, "y": 277}, {"x": 452, "y": 299}, {"x": 435, "y": 297}]}}, {"description": "\u5229", "boundingPoly": {"vertices": [{"x": 457, "y": 278}, {"x": 470, "y": 280}, {"x": 467, "y": 302}, {"x": 454, "y": 300}]}}, {"description": "(", "boundingPoly": {"vertices": [{"x": 472, "y": 280}, {"x": 486, "y": 282}, {"x": 483, "y": 304}, {"x": 469, "y": 302}]}}, {"description": "\u78bc", "boundingPoly": {"vertices": [{"x": 488, "y": 282}, {"x": 521, "y": 286}, {"x": 518, "y": 308}, {"x": 485, "y": 304}]}}, {"description": "\u4fee", "boundingPoly": {"vertices": [{"x": 522, "y": 287}, {"x": 538, "y": 289}, {"x": 535, "y": 311}, {"x": 519, "y": 309}]}}, {"description": "Na", "boundingPoly": {"vertices": [{"x": 537, "y": 294}, {"x": 563, "y": 297}, {"x": 561, "y": 310}, {"x": 535, "y": 307}]}}, {"description": ")", "boundingPoly": {"vertices": [{"x": 571, "y": 293}, {"x": 584, "y": 295}, {"x": 581, "y": 314}, {"x": 568, "y": 312}]}}, {"description": "\u6750", "boundingPoly": {"vertices": [{"x": 240, "y": 270}, {"x": 267, "y": 273}, {"x": 264, "y": 295}, {"x": 237, "y": 292}]}}, {"description": "\u4e00\u90e8", "boundingPoly": {"vertices": [{"x": 269, "y": 274}, {"x": 332, "y": 282}, {"x": 329, "y": 304}, {"x": 266, "y": 296}]}}, {"description": "\u306b", "boundingPoly": {"vertices": [{"x": 334, "y": 282}, {"x": 347, "y": 284}, {"x": 344, "y": 305}, {"x": 331, "y": 304}]}}, {"description": "\u3001", "boundingPoly": {"vertices": [{"x": 349, "y": 284}, {"x": 381, "y": 288}, {"x": 378, "y": 310}, {"x": 346, "y": 306}]}}, {"description": "\u5c0f\u9ea6", "boundingPoly": {"vertices": [{"x": 383, "y": 288}, {"x": 420, "y": 293}, {"x": 417, "y": 314}, {"x": 380, "y": 310}]}}, {"description": "\u3001", "boundingPoly": {"vertices": [{"x": 421, "y": 293}, {"x": 426, "y": 294}, {"x": 423, "y": 315}, {"x": 418, "y": 315}]}}, {"description": "\u8c5a", "boundingPoly": {"vertices": [{"x": 428, "y": 294}, {"x": 449, "y": 297}, {"x": 446, "y": 318}, {"x": 425, "y": 316}]}}, {"description": "\u8089", "boundingPoly": {"vertices": [{"x": 451, "y": 297}, {"x": 469, "y": 299}, {"x": 466, "y": 321}, {"x": 448, "y": 319}]}}, {"description": "\u3092", "boundingPoly": {"vertices": [{"x": 471, "y": 300}, {"x": 484, "y": 302}, {"x": 481, "y": 323}, {"x": 468, "y": 322}]}}, {"description": "\u542b", "boundingPoly": {"vertices": [{"x": 486, "y": 302}, {"x": 499, "y": 304}, {"x": 496, "y": 325}, {"x": 483, "y": 324}]}}, {"description": "\u3080", "boundingPoly": {"vertices": [{"x": 501, "y": 303}, {"x": 518, "y": 305}, {"x": 515, "y": 327}, {"x": 498, "y": 325}]}}, {"description": ")", "boundingPoly": {"vertices": [{"x": 520, "y": 306}, {"x": 522, "y": 306}, {"x": 519, "y": 328}, {"x": 517, "y": 328}]}}, {"description": "\u8b70", "boundingPoly": {"vertices": [{"x": 265, "y": 294}, {"x": 285, "y": 297}, {"x": 282, "y": 319}, {"x": 262, "y": 317}]}}, {"description": "19", "boundingPoly": {"vertices": [{"x": 301, "y": 302}, {"x": 322, "y": 305}, {"x": 319, "y": 325}, {"x": 298, "y": 322}]}}, {"description": "96", "boundingPoly": {"vertices": [{"x": 333, "y": 306}, {"x": 368, "y": 310}, {"x": 365, "y": 330}, {"x": 330, "y": 326}]}}, {"description": "\u5348\u5f8c", "boundingPoly": {"vertices": [{"x": 383, "y": 312}, {"x": 442, "y": 320}, {"x": 439, "y": 339}, {"x": 380, "y": 332}]}}, {"description": "48", "boundingPoly": {"vertices": [{"x": 444, "y": 317}, {"x": 475, "y": 321}, {"x": 472, "y": 344}, {"x": 441, "y": 340}]}}, {"description": "\u6642", "boundingPoly": {"vertices": [{"x": 477, "y": 321}, {"x": 483, "y": 322}, {"x": 480, "y": 345}, {"x": 474, "y": 344}]}}, {"description": "\u4fdd\u5b58", "boundingPoly": {"vertices": [{"x": 204, "y": 306}, {"x": 248, "y": 312}, {"x": 245, "y": 332}, {"x": 201, "y": 327}]}}, {"description": "\u65b9\u6cd5", "boundingPoly": {"vertices": [{"x": 250, "y": 312}, {"x": 285, "y": 316}, {"x": 282, "y": 337}, {"x": 247, "y": 333}]}}, {"description": "\u5c04", "boundingPoly": {"vertices": [{"x": 286, "y": 317}, {"x": 328, "y": 322}, {"x": 325, "y": 343}, {"x": 283, "y": 338}]}}, {"description": "\u65e5\u5149", "boundingPoly": {"vertices": [{"x": 330, "y": 322}, {"x": 365, "y": 326}, {"x": 362, "y": 347}, {"x": 327, "y": 343}]}}, {"description": "\u53ca\u3073", "boundingPoly": {"vertices": [{"x": 367, "y": 327}, {"x": 398, "y": 331}, {"x": 395, "y": 352}, {"x": 364, "y": 348}]}}, {"description": "\u4e8b", "boundingPoly": {"vertices": [{"x": 399, "y": 331}, {"x": 444, "y": 337}, {"x": 441, "y": 358}, {"x": 396, "y": 352}]}}, {"description": "\u6e29", "boundingPoly": {"vertices": [{"x": 443, "y": 340}, {"x": 457, "y": 342}, {"x": 455, "y": 357}, {"x": 441, "y": 355}]}}, {"description": "\u3092", "boundingPoly": {"vertices": [{"x": 461, "y": 343}, {"x": 472, "y": 344}, {"x": 470, "y": 358}, {"x": 459, "y": 357}]}}, {"description": "\u907f\u3051", "boundingPoly": {"vertices": [{"x": 476, "y": 341}, {"x": 507, "y": 345}, {"x": 504, "y": 363}, {"x": 474, "y": 359}]}}, {"description": "\u3066", "boundingPoly": {"vertices": [{"x": 508, "y": 345}, {"x": 531, "y": 348}, {"x": 528, "y": 369}, {"x": 505, "y": 366}]}}, {"description": "\u4e0b\u3055\u3044", "boundingPoly": {"vertices": [{"x": 533, "y": 348}, {"x": 572, "y": 353}, {"x": 569, "y": 375}, {"x": 530, "y": 370}]}}, {"description": "PJ23", "boundingPoly": {"vertices": [{"x": 564, "y": 337}, {"x": 593, "y": 341}, {"x": 590, "y": 357}, {"x": 562, "y": 353}]}}, {"description": "0120-634058", "boundingPoly": {"vertices": [{"x": 496, "y": 362}, {"x": 583, "y": 372}, {"x": 581, "y": 391}, {"x": 494, "y": 381}]}}, {"description": "11", "boundingPoly": {"vertices": [{"x": 257, "y": 350}, {"x": 349, "y": 362}, {"x": 347, "y": 381}, {"x": 254, "y": 369}]}}, {"description": "2-48", "boundingPoly": {"vertices": [{"x": 354, "y": 362}, {"x": 407, "y": 369}, {"x": 404, "y": 389}, {"x": 351, "y": 382}]}}, {"description": "1", "boundingPoly": {"vertices": [{"x": 195, "y": 367}, {"x": 217, "y": 370}, {"x": 214, "y": 392}, {"x": 192, "y": 389}]}}, {"description": "2", "boundingPoly": {"vertices": [{"x": 219, "y": 370}, {"x": 228, "y": 371}, {"x": 225, "y": 393}, {"x": 216, "y": 392}]}}, {"description": "U", "boundingPoly": {"vertices": [{"x": 272, "y": 378}, {"x": 281, "y": 379}, {"x": 278, "y": 401}, {"x": 269, "y": 400}]}}, {"description": "PA9", "boundingPoly": {"vertices": [{"x": 286, "y": 381}, {"x": 348, "y": 389}, {"x": 346, "y": 409}, {"x": 283, "y": 401}]}}, {"description": "2kcal", "boundingPoly": {"vertices": [{"x": 354, "y": 392}, {"x": 391, "y": 397}, {"x": 388, "y": 416}, {"x": 351, "y": 411}]}}, {"description": "\u70ad", "boundingPoly": {"vertices": [{"x": 201, "y": 388}, {"x": 221, "y": 391}, {"x": 218, "y": 410}, {"x": 198, "y": 407}]}}, {"description": "\u6c34\u5316", "boundingPoly": {"vertices": [{"x": 223, "y": 391}, {"x": 249, "y": 395}, {"x": 246, "y": 414}, {"x": 220, "y": 410}]}}, {"description": "\u7269", "boundingPoly": {"vertices": [{"x": 250, "y": 395}, {"x": 265, "y": 397}, {"x": 262, "y": 416}, {"x": 247, "y": 414}]}}, {"description": "37.4g", "boundingPoly": {"vertices": [{"x": 267, "y": 397}, {"x": 325, "y": 405}, {"x": 323, "y": 425}, {"x": 264, "y": 417}]}}, {"description": "Na", "boundingPoly": {"vertices": [{"x": 332, "y": 411}, {"x": 357, "y": 415}, {"x": 355, "y": 426}, {"x": 330, "y": 423}]}}, {"description": "21", "boundingPoly": {"vertices": [{"x": 366, "y": 414}, {"x": 385, "y": 417}, {"x": 383, "y": 431}, {"x": 364, "y": 428}]}}, {"description": "8g", "boundingPoly": {"vertices": [{"x": 398, "y": 418}, {"x": 424, "y": 422}, {"x": 422, "y": 437}, {"x": 396, "y": 433}]}}, {"description": "8g", "boundingPoly": {"vertices": [{"x": 451, "y": 402}, {"x": 498, "y": 408}, {"x": 495, "y": 430}, {"x": 448, "y": 424}]}}, {"description": "M2", "boundingPoly": {"vertices": [{"x": 503, "y": 411}, {"x": 548, "y": 417}, {"x": 545, "y": 434}, {"x": 501, "y": 428}]}}, {"description": "68", "boundingPoly": {"vertices": [{"x": 560, "y": 419}, {"x": 580, "y": 422}, {"x": 577, "y": 440}, {"x": 558, "y": 437}]}}], "fullTextAnnotation": {"pages": [{"property": {"detectedLanguages": [{"languageCode": "ja", "confidence": 0.54}, {"languageCode": "en", "confidence": 0.11}, {"languageCode": "zh", "confidence": 0.09}]}, "width": 640, "height": 480, "blocks": [{"property": {"detectedLanguages": [{"languageCode": "ja", "confidence": 0.28}]}, "boundingBox": {"vertices": [{"x": 238, "y": 159}, {"x": 351, "y": 162}, {"x": 350, "y": 199}, {"x": 237, "y": 196}]}, "paragraphs": [{"property": {"detectedLanguages": [{"languageCode": "ja", "confidence": 0.28}]}, "boundingBox": {"vertices": [{"x": 238, "y": 159}, {"x": 351, "y": 162}, {"x": 350, "y": 199}, {"x": 237, "y": 196}]}, "words": [{"boundingBox": {"vertices": [{"x": 250, "y": 160}, {"x": 284, "y": 161}, {"x": 284, "y": 179}, {"x": 250, "y": 178}]}, "symbols": [{"boundingBox": {"vertices": [{"x": 250, "y": 160}, {"x": 262, "y": 160}, {"x": 262, "y": 178}, {"x": 250, "y": 178}]}, "text": "2"}, {"boundingBox": {"vertices": [{"x": 263, "y": 160}, {"x": 265, "y": 160}, {"x": 265, "y": 178}, {"x": 263, "y": 178}]}, "text": "0"}, {"boundingBox": {"vertices": [{"x": 266, "y": 160}, {"x": 271, "y": 160}, {"x": 271, "y": 178}, {"x": 266, "y": 178}]}, "text": "4"}, {"boundingBox": {"vertices": [{"x": 272, "y": 161}, {"x": 278, "y": 161}, {"x": 278, "y": 179}, {"x": 272, "y": 179}]}, "text": "4"}, {"property": {"detectedBreak": {"type": "SPACE"}}, "boundingBox": {"vertices": [{"x": 279, "y": 161}, {"x": 284, "y": 161}, {"x": 284, "y": 179}, {"x": 279, "y": 179}]}, "text": "7"}]}, {"boundingBox": {"vertices": [{"x": 286, "y": 160}, {"x": 341, "y": 161}, {"x": 341, "y": 179}, {"x": 286, "y": 178}]}, "symbols": [{"boundingBox": {"vertices": [{"x": 286, "y": 160}, {"x": 290, "y": 160}, {"x": 290, "y": 178}, {"x": 286, "y": 178}]}, "text": "8"}, {"boundingBox": {"vertices": [{"x": 291, "y": 161}, {"x": 297, "y": 161}, {"x": 297, "y": 179}, {"x": 291, "y": 179}]}, "text": "0"}, {"boundingBox": {"vertices": [{"x": 298, "y": 161}, {"x": 303, "y": 161}, {"x": 303, "y": 179}, {"x": 298, "y": 179}]}, "text": "3"}, {"boundingBox": {"vertices": [{"x": 304, "y": 161}, {"x": 313, "y": 161}, {"x": 313, "y": 179}, {"x": 304, "y": 179}]}, "text": "0"}, {"boundingBox": {"vertices": [{"x": 314, "y": 162}, {"x": 319, "y": 162}, {"x": 319, "y": 180}, {"x": 314, "y": 180}]}, "text": "1"}, {"boundingBox": {"vertices": [{"x": 320, "y": 162}, {"x": 325, "y": 162}, {"x": 325, "y": 180}, {"x": 320, "y": 180}]}, "text": "4"}, {"boundingBox": {"vertices": [{"x": 326, "y": 162}, {"x": 332, "y": 162}, {"x": 332, "y": 180}, {"x": 326, "y": 180}]}, "text": "4"}, {"property": {"detectedBreak": {"type": "EOL_SURE_SPACE"}}, "boundingBox": {"vertices": [{"x": 333, "y": 162}, {"x": 341, "y": 162}, {"x": 341, "y": 180}, {"x": 333, "y": 180}]}, "text": "3"}]}, {"property": {"detectedLanguages": [{"languageCode": "ja"}]}, "boundingBox": {"vertices": [{"x": 238, "y": 174}, {"x": 272, "y": 175}, {"x": 271, "y": 196}, {"x": 237, "y": 195}]}, "symbols": [{"property": {"detectedLanguages": [{"languageCode": "ja"}]}, "boundingBox": {"vertices": [{"x": 238, "y": 174}, {"x": 238, "y": 174}, {"x": 238, "y": 174}, {"x": 238, "y": 174}]}, "text": "\u540d"}, {"property": {"detectedLanguages": [{"languageCode": "ja"}]}, "boundingBox": {"vertices": [{"x": 243, "y": 174}, {"x": 272, "y": 175}, {"x": 271, "y": 196}, {"x": 242, "y": 195}]}, "text": "\u79f0"}]}, {"property": {"detectedLanguages": [{"languageCode": "ja"}]}, "boundingBox": {"vertices": [{"x": 284, "y": 179}, {"x": 351, "y": 182}, {"x": 350, "y": 200}, {"x": 283, "y": 197}]}, "symbols": [{"property": {"detectedLanguages": [{"languageCode": "ja"}]}, "boundingBox": {"vertices": [{"x": 284, "y": 179}, {"x": 304, "y": 180}, {"x": 303, "y": 198}, {"x": 283, "y": 197}]}, "text": "\u304a"}, {"property": {"detectedLanguages": [{"languageCode": "ja"}]}, "boundingBox": {"vertices": [{"x": 305, "y": 180}, {"x": 323, "y": 181}, {"x": 322, "y": 199}, {"x": 304, "y": 198}]}, "text": "\u306b"}, {"property": {"detectedLanguages": [{"languageCode": "ja"}], "detectedBreak": {"type": "EOL_SURE_SPACE"}}, "boundingBox": {"vertices": [{"x": 324, "y": 181}, {"x": 351, "y": 182}, {"x": 350, "y": 200}, {"x": 323, "y": 199}]}, "text": "\u308a"}]}]}], "blockType": "TEXT"}, {"property": {"detectedLanguages": [{"languageCode": "ja", "confidence": 0.7}]}, "boundingBox": {"vertices": [{"x": 411, "y": 158}, {"x": 596, "y": 201}, {"x": 585, "y": 247}, {"x": 400, "y": 205}]}, "paragraphs": [{"property": {"detectedLanguages": [{"languageCode": "ja", "confidence": 0.7}]}, "boundingBox": {"vertices": [{"x": 411, "y": 158}, {"x": 596, "y": 201}, {"x": 585, "y": 247}, {"x": 400, "y": 205}]}, "words": [{"boundingBox": {"vertices": [{"x": 553, "y": 191}, {"x": 591, "y": 200}, {"x": 586, "y": 219}, {"x": 548, "y": 209}]}, "symbols": [{"boundingBox": {"vertices": [{"x": 553, "y": 191}, {"x": 573, "y": 196}, {"x": 569, "y": 215}, {"x": 548, "y": 209}]}, "text": "Y"}, {"boundingBox": {"vertices": [{"x": 574, "y": 196}, {"x": 584, "y": 198}, {"x": 579, "y": 217}, {"x": 569, "y": 214}]}, "text": "1"}, {"property": {"detectedBreak": {"type": "EOL_SURE_SPACE"}}, "boundingBox": {"vertices": [{"x": 585, "y": 199}, {"x": 591, "y": 200}, {"x": 586, "y": 219}, {"x": 580, "y": 217}]}, "text": "4"}]}, {"property": {"detectedLanguages": [{"languageCode": "ja"}]}, "boundingBox": {"vertices": [{"x": 405, "y": 183}, {"x": 501, "y": 201}, {"x": 497, "y": 224}, {"x": 401, "y": 206}]}, "symbols": [{"property": {"detectedLanguages": [{"languageCode": "ja"}]}, "boundingBox": {"vertices": [{"x": 405, "y": 183}, {"x": 439, "y": 189}, {"x": 435, "y": 211}, {"x": 401, "y": 205}]}, "text": "\u30d9"}, {"property": {"detectedLanguages": [{"languageCode": "ja"}]}, "boundingBox": {"vertices": [{"x": 440, "y": 190}, {"x": 466, "y": 195}, {"x": 462, "y": 216}, {"x": 436, "y": 212}]}, "text": "\u30fc"}, {"property": {"detectedLanguages": [{"languageCode": "ja"}]}, "boundingBox": {"vertices": [{"x": 467, "y": 195}, {"x": 493, "y": 200}, {"x": 489, "y": 221}, {"x": 463, "y": 217}]}, "text": "\u30b3"}, {"property": {"detectedLanguages": [{"languageCode": "ja"}], "detectedBreak": {"type": "SPACE"}}, "boundingBox": {"vertices": [{"x": 493, "y": 200}, {"x": 501, "y": 201}, {"x": 497, "y": 223}, {"x": 489, "y": 222}]}, "text": "\u30f3"}]}, {"property": {"detectedLanguages": [{"languageCode": "ja"}]}, "boundingBox": {"vertices": [{"x": 527, "y": 205}, {"x": 591, "y": 217}, {"x": 587, "y": 240}, {"x": 523, "y": 228}]}, "symbols": [{"property": {"detectedLanguages": [{"languageCode": "ja"}]}, "boundingBox": {"vertices": [{"x": 527, "y": 206}, {"x": 545, "y": 209}, {"x": 541, "y": 231}, {"x": 523, "y": 228}]}, "text": "\u305f"}, {"property": {"detectedLanguages": [{"languageCode": "ja"}]}, "boundingBox": {"vertices": [{"x": 546, "y": 209}, {"x": 586, "y": 217}, {"x": 582, "y": 238}, {"x": 542, "y": 231}]}, "text": "\u307e"}, {"property": {"detectedLanguages": [{"languageCode": "ja"}], "detectedBreak": {"type": "EOL_SURE_SPACE"}}, "boundingBox": {"vertices": [{"x": 587, "y": 217}, {"x": 591, "y": 218}, {"x": 587, "y": 239}, {"x": 583, "y": 239}]}, "text": "\u3054"}]}]}], "blockType": "TEXT"}, {"property": {"detectedLanguages": [{"languageCode": "ja", "confidence": 1}]}, "boundingBox": {"vertices": [{"x": 238, "y": 207}, {"x": 593, "y": 254}, {"x": 590, "y": 277}, {"x": 235, "y": 230}]}, "paragraphs": [{"property": {"detectedLanguages": [{"languageCode": "ja", "confidence": 1}]}, "boundingBox": {"vertices": [{"x": 238, "y": 207}, {"x": 593, "y": 254}, {"x": 590, "y": 277}, {"x": 235, "y": 230}]}, "words": [{"property": {"detectedLanguages": [{"languageCode": "ja"}]}, "boundingBox": {"vertices": [{"x": 238, "y": 207}, {"x": 315, "y": 217}, {"x": 312, "y": 240}, {"x": 235, "y": 230}]}, "symbols": [{"property": {"detectedLanguages": [{"languageCode": "ja"}]}, "boundingBox": {"vertices": [{"x": 238, "y": 207}, {"x": 264, "y": 210}, {"x": 261, "y": 233}, {"x": 235, "y": 230}]}, "text": "\u3048"}, {"property": {"detectedLanguages": [{"languageCode": "ja"}]}, "boundingBox": {"vertices": [{"x": 265, "y": 211}, {"x": 300, "y": 216}, {"x": 297, "y": 238}, {"x": 262, "y": 234}]}, "text": "\u3054"}, {"property": {"detectedLanguages": [{"languageCode": "ja"}]}, "boundingBox": {"vertices": [{"x": 300, "y": 215}, {"x": 315, "y": 217}, {"x": 312, "y": 240}, {"x": 297, "y": 238}]}, "text": "\u307e"}]}, {"property": {"detectedLanguages": [{"languageCode": "ja"}]}, "boundingBox": {"vertices": [{"x": 317, "y": 218}, {"x": 347, "y": 222}, {"x": 344, "y": 245}, {"x": 314, "y": 241}]}, "symbols": [{"property": {"detectedLanguages": [{"languageCode": "ja"}]}, "boundingBox": {"vertices": [{"x": 317, "y": 218}, {"x": 327, "y": 219}, {"x": 324, "y": 242}, {"x": 314, "y": 241}]}, "text": "\u5165"}, {"property": {"detectedLanguages": [{"languageCode": "ja"}]}, "boundingBox": {"vertices": [{"x": 328, "y": 220}, {"x": 347, "y": 223}, {"x": 344, "y": 245}, {"x": 325, "y": 243}]}, "text": "\u308a"}]}, {"property": {"detectedLanguages": [{"languageCode": "ja"}]}, "boundingBox": {"vertices": [{"x": 349, "y": 221}, {"x": 409, "y": 229}, {"x": 406, "y": 253}, {"x": 346, "y": 245}]}, "symbols": [{"property": {"detectedLanguages": [{"languageCode": "ja"}]}, "boundingBox": {"vertices": [{"x": 349, "y": 222}, {"x": 363, "y": 224}, {"x": 360, "y": 247}, {"x": 346, "y": 245}]}, "text": "\u30d9"}, {"property": {"detectedLanguages": [{"languageCode": "ja"}]}, "boundingBox": {"vertices": [{"x": 364, "y": 224}, {"x": 367, "y": 224}, {"x": 364, "y": 247}, {"x": 361, "y": 247}]}, "text": "\u30fc"}, {"property": {"detectedLanguages": [{"languageCode": "ja"}]}, "boundingBox": {"vertices": [{"x": 368, "y": 224}, {"x": 403, "y": 229}, {"x": 400, "y": 251}, {"x": 365, "y": 247}]}, "text": "\u30b3"}, {"property": {"detectedLanguages": [{"languageCode": "ja"}]}, "boundingBox": {"vertices": [{"x": 403, "y": 229}, {"x": 410, "y": 230}, {"x": 407, "y": 253}, {"x": 400, "y": 252}]}, "text": "\u30f3"}]}, {"property": {"detectedLanguages": [{"languageCode": "ja"}]}, "boundingBox": {"vertices": [{"x": 412, "y": 230}, {"x": 430, "y": 232}, {"x": 427, "y": 255}, {"x": 409, "y": 253}]}, "symbols": [{"property": {"detectedLanguages": [{"languageCode": "ja"}]}, "boundingBox": {"vertices": [{"x": 412, "y": 230}, {"x": 430, "y": 232}, {"x": 427, "y": 255}, {"x": 409, "y": 253}]}, "text": "\u63d0"}]}, {"property": {"detectedLanguages": [{"languageCode": "ja"}]}, "boundingBox": {"vertices": [{"x": 432, "y": 233}, {"x": 442, "y": 234}, {"x": 439, "y": 257}, {"x": 429, "y": 256}]}, "symbols": [{"property": {"detectedLanguages": [{"languageCode": "ja"}]}, "boundingBox": {"vertices": [{"x": 432, "y": 233}, {"x": 442, "y": 234}, {"x": 439, "y": 257}, {"x": 429, "y": 256}]}, "text": "\u304d"}]}, {"property": {"detectedLanguages": [{"languageCode": "ja"}]}, "boundingBox": {"vertices": [{"x": 440, "y": 249}, {"x": 442, "y": 249}, {"x": 442, "y": 250}, {"x": 440, "y": 250}]}, "symbols": [{"property": {"detectedLanguages": [{"languageCode": "ja"}], "detectedBreak": {"type": "SPACE"}}, "boundingBox": {"vertices": [{"x": 440, "y": 249}, {"x": 442, "y": 249}, {"x": 442, "y": 250}, {"x": 440, "y": 250}]}, "text": "\u3001"}]}, {"property": {"detectedLanguages": [{"languageCode": "ja"}]}, "boundingBox": {"vertices": [{"x": 459, "y": 239}, {"x": 494, "y": 244}, {"x": 491, "y": 264}, {"x": 456, "y": 260}]}, "symbols": [{"property": {"detectedLanguages": [{"languageCode": "ja"}]}, "boundingBox": {"vertices": [{"x": 459, "y": 239}, {"x": 494, "y": 244}, {"x": 491, "y": 264}, {"x": 456, "y": 260}]}, "text": "\u3001"}]}, {"property": {"detectedLanguages": [{"languageCode": "ja"}]}, "boundingBox": {"vertices": [{"x": 507, "y": 243}, {"x": 545, "y": 248}, {"x": 542, "y": 271}, {"x": 504, "y": 266}]}, "symbols": [{"property": {"detectedLanguages": [{"languageCode": "ja"}]}, "boundingBox": {"vertices": [{"x": 507, "y": 243}, {"x": 529, "y": 246}, {"x": 526, "y": 269}, {"x": 504, "y": 266}]}, "text": "D"}, {"property": {"detectedLanguages": [{"languageCode": "ja"}]}, "boundingBox": {"vertices": [{"x": 530, "y": 246}, {"x": 545, "y": 248}, {"x": 542, "y": 271}, {"x": 527, "y": 269}]}, "text": "H"}]}, {"property": {"detectedLanguages": [{"languageCode": "ja"}]}, "boundingBox": {"vertices": [{"x": 547, "y": 248}, {"x": 593, "y": 254}, {"x": 590, "y": 277}, {"x": 544, "y": 271}]}, "symbols": [{"property": {"detectedLanguages": [{"languageCode": "ja"}], "detectedBreak": {"type": "EOL_SURE_SPACE"}}, "boundingBox": {"vertices": [{"x": 547, "y": 248}, {"x": 593, "y": 254}, {"x": 590, "y": 277}, {"x": 544, "y": 271}]}, "text": "\u79c1"}]}]}], "blockType": "TEXT"}, {"boundingBox": {"vertices": [{"x": 487, "y": 261}, {"x": 549, "y": 269}, {"x": 546, "y": 292}, {"x": 484, "y": 284}]}, "paragraphs": [{"boundingBox": {"vertices": [{"x": 487, "y": 261}, {"x": 549, "y": 269}, {"x": 546, "y": 292}, {"x": 484, "y": 284}]}, "words": [{"boundingBox": {"vertices": [{"x": 487, "y": 261}, {"x": 500, "y": 263}, {"x": 497, "y": 285}, {"x": 484, "y": 283}]}, "symbols": [{"property": {"detectedBreak": {"type": "SPACE"}}, "boundingBox": {"vertices": [{"x": 487, "y": 261}, {"x": 500, "y": 263}, {"x": 497, "y": 285}, {"x": 484, "y": 283}]}, "text": "A"}]}, {"boundingBox": {"vertices": [{"x": 529, "y": 267}, {"x": 549, "y": 270}, {"x": 546, "y": 291}, {"x": 526, "y": 289}]}, "symbols": [{"boundingBox": {"vertices": [{"x": 529, "y": 267}, {"x": 541, "y": 269}, {"x": 538, "y": 290}, {"x": 526, "y": 289}]}, "text": "("}, {"property": {"detectedBreak": {"type": "EOL_SURE_SPACE"}}, "boundingBox": {"vertices": [{"x": 542, "y": 269}, {"x": 549, "y": 270}, {"x": 546, "y": 292}, {"x": 539, "y": 291}]}, "text": "7"}]}]}], "blockType": "TEXT"}, {"property": {"detectedLanguages": [{"languageCode": "ja", "confidence": 1}]}, "boundingBox": {"vertices": [{"x": 212, "y": 245}, {"x": 584, "y": 293}, {"x": 573, "y": 375}, {"x": 201, "y": 327}]}, "paragraphs": [{"property": {"detectedLanguages": [{"languageCode": "ja", "confidence": 1}]}, "boundingBox": {"vertices": [{"x": 212, "y": 245}, {"x": 584, "y": 293}, {"x": 573, "y": 375}, {"x": 201, "y": 327}]}, "words": [{"property": {"detectedLanguages": [{"languageCode": "ja"}]}, "boundingBox": {"vertices": [{"x": 222, "y": 246}, {"x": 239, "y": 248}, {"x": 236, "y": 269}, {"x": 219, "y": 267}]}, "symbols": [{"property": {"detectedLanguages": [{"languageCode": "ja"}], "detectedBreak": {"type": "SPACE"}}, "boundingBox": {"vertices": [{"x": 222, "y": 246}, {"x": 239, "y": 248}, {"x": 236, "y": 269}, {"x": 219, "y": 267}]}, "text": "\u7b49"}]}, {"property": {"detectedLanguages": [{"languageCode": "ja"}]}, "boundingBox": {"vertices": [{"x": 293, "y": 262}, {"x": 315, "y": 265}, {"x": 313, "y": 278}, {"x": 291, "y": 275}]}, "symbols": [{"property": {"detectedLanguages": [{"languageCode": "ja"}]}, "boundingBox": {"vertices": [{"x": 293, "y": 262}, {"x": 315, "y": 265}, {"x": 313, "y": 278}, {"x": 291, "y": 275}]}, "text": "\u30b7"}]}, {"property": {"detectedLanguages": [{"languageCode": "ja"}]}, "boundingBox": {"vertices": [{"x": 319, "y": 265}, {"x": 337, "y": 267}, {"x": 335, "y": 280}, {"x": 317, "y": 278}]}, "symbols": [{"property": {"detectedLanguages": [{"languageCode": "ja"}]}, "boundingBox": {"vertices": [{"x": 319, "y": 265}, {"x": 337, "y": 267}, {"x": 335, "y": 280}, {"x": 317, "y": 278}]}, "text": "\u30f3"}]}, {"property": {"detectedLanguages": [{"languageCode": "ja"}]}, "boundingBox": {"vertices": [{"x": 340, "y": 262}, {"x": 345, "y": 263}, {"x": 342, "y": 284}, {"x": 337, "y": 284}]}, "symbols": [{"property": {"detectedLanguages": [{"languageCode": "ja"}]}, "boundingBox": {"vertices": [{"x": 340, "y": 262}, {"x": 345, "y": 263}, {"x": 342, "y": 284}, {"x": 337, "y": 284}]}, "text": "\u3001"}]}, {"property": {"detectedLanguages": [{"languageCode": "ja"}]}, "boundingBox": {"vertices": [{"x": 352, "y": 267}, {"x": 362, "y": 268}, {"x": 360, "y": 284}, {"x": 350, "y": 283}]}, "symbols": [{"property": {"detectedLanguages": [{"languageCode": "ja"}]}, "boundingBox": {"vertices": [{"x": 352, "y": 267}, {"x": 362, "y": 268}, {"x": 360, "y": 284}, {"x": 350, "y": 283}]}, "text": "\u304f"}]}, {"property": {"detectedLanguages": [{"languageCode": "ja"}]}, "boundingBox": {"vertices": [{"x": 370, "y": 266}, {"x": 383, "y": 268}, {"x": 380, "y": 290}, {"x": 367, "y": 288}]}, "symbols": [{"property": {"detectedLanguages": [{"languageCode": "ja"}]}, "boundingBox": {"vertices": [{"x": 370, "y": 266}, {"x": 383, "y": 268}, {"x": 380, "y": 290}, {"x": 367, "y": 288}]}, "text": "\u3093"}]}, {"property": {"detectedLanguages": [{"languageCode": "ja"}]}, "boundingBox": {"vertices": [{"x": 384, "y": 268}, {"x": 409, "y": 271}, {"x": 406, "y": 293}, {"x": 381, "y": 290}]}, "symbols": [{"property": {"detectedLanguages": [{"languageCode": "ja"}]}, "boundingBox": {"vertices": [{"x": 384, "y": 268}, {"x": 409, "y": 271}, {"x": 406, "y": 293}, {"x": 381, "y": 290}]}, "text": "\u591c"}]}, {"property": {"detectedLanguages": [{"languageCode": "ja"}]}, "boundingBox": {"vertices": [{"x": 411, "y": 273}, {"x": 436, "y": 276}, {"x": 433, "y": 298}, {"x": 408, "y": 295}]}, "symbols": [{"property": {"detectedLanguages": [{"languageCode": "ja"}]}, "boundingBox": {"vertices": [{"x": 411, "y": 273}, {"x": 436, "y": 276}, {"x": 433, "y": 298}, {"x": 408, "y": 295}]}, "text": "\u767a"}]}, {"property": {"detectedLanguages": [{"languageCode": "ja"}]}, "boundingBox": {"vertices": [{"x": 438, "y": 275}, {"x": 455, "y": 277}, {"x": 452, "y": 299}, {"x": 435, "y": 297}]}, "symbols": [{"property": {"detectedLanguages": [{"languageCode": "ja"}]}, "boundingBox": {"vertices": [{"x": 438, "y": 275}, {"x": 455, "y": 277}, {"x": 452, "y": 299}, {"x": 435, "y": 297}]}, "text": "\u8272"}]}, {"property": {"detectedLanguages": [{"languageCode": "ja"}]}, "boundingBox": {"vertices": [{"x": 457, "y": 278}, {"x": 470, "y": 280}, {"x": 467, "y": 302}, {"x": 454, "y": 300}]}, "symbols": [{"property": {"detectedLanguages": [{"languageCode": "ja"}]}, "boundingBox": {"vertices": [{"x": 457, "y": 278}, {"x": 470, "y": 280}, {"x": 467, "y": 302}, {"x": 454, "y": 300}]}, "text": "\u5229"}]}, {"property": {"detectedLanguages": [{"languageCode": "ja"}]}, "boundingBox": {"vertices": [{"x": 472, "y": 280}, {"x": 486, "y": 282}, {"x": 483, "y": 304}, {"x": 469, "y": 302}]}, "symbols": [{"property": {"detectedLanguages": [{"languageCode": "ja"}]}, "boundingBox": {"vertices": [{"x": 472, "y": 280}, {"x": 486, "y": 282}, {"x": 483, "y": 304}, {"x": 469, "y": 302}]}, "text": "("}]}, {"property": {"detectedLanguages": [{"languageCode": "ja"}]}, "boundingBox": {"vertices": [{"x": 488, "y": 282}, {"x": 521, "y": 286}, {"x": 518, "y": 308}, {"x": 485, "y": 304}]}, "symbols": [{"property": {"detectedLanguages": [{"languageCode": "ja"}]}, "boundingBox": {"vertices": [{"x": 488, "y": 282}, {"x": 521, "y": 286}, {"x": 518, "y": 308}, {"x": 485, "y": 304}]}, "text": "\u78bc"}]}, {"property": {"detectedLanguages": [{"languageCode": "ja"}]}, "boundingBox": {"vertices": [{"x": 522, "y": 287}, {"x": 538, "y": 289}, {"x": 535, "y": 311}, {"x": 519, "y": 309}]}, "symbols": [{"property": {"detectedLanguages": [{"languageCode": "ja"}], "detectedBreak": {"type": "SPACE"}}, "boundingBox": {"vertices": [{"x": 522, "y": 287}, {"x": 538, "y": 289}, {"x": 535, "y": 311}, {"x": 519, "y": 309}]}, "text": "\u4fee"}]}, {"property": {"detectedLanguages": [{"languageCode": "ja"}]}, "boundingBox": {"vertices": [{"x": 537, "y": 294}, {"x": 563, "y": 297}, {"x": 561, "y": 310}, {"x": 535, "y": 307}]}, "symbols": [{"property": {"detectedLanguages": [{"languageCode": "ja"}]}, "boundingBox": {"vertices": [{"x": 537, "y": 294}, {"x": 547, "y": 295}, {"x": 545, "y": 307}, {"x": 535, "y": 306}]}, "text": "N"}, {"property": {"detectedLanguages": [{"languageCode": "ja"}]}, "boundingBox": {"vertices": [{"x": 553, "y": 299}, {"x": 562, "y": 300}, {"x": 561, "y": 310}, {"x": 552, "y": 309}]}, "text": "a"}]}, {"property": {"detectedLanguages": [{"languageCode": "ja"}]}, "boundingBox": {"vertices": [{"x": 571, "y": 293}, {"x": 584, "y": 295}, {"x": 581, "y": 314}, {"x": 568, "y": 312}]}, "symbols": [{"property": {"detectedLanguages": [{"languageCode": "ja"}], "detectedBreak": {"type": "EOL_SURE_SPACE"}}, "boundingBox": {"vertices": [{"x": 571, "y": 293}, {"x": 584, "y": 295}, {"x": 581, "y": 314}, {"x": 568, "y": 312}]}, "text": ")"}]}, {"property": {"detectedLanguages": [{"languageCode": "ja"}]}, "boundingBox": {"vertices": [{"x": 240, "y": 270}, {"x": 267, "y": 273}, {"x": 264, "y": 295}, {"x": 237, "y": 292}]}, "symbols": [{"property": {"detectedLanguages": [{"languageCode": "ja"}]}, "boundingBox": {"vertices": [{"x": 240, "y": 270}, {"x": 267, "y": 273}, {"x": 264, "y": 295}, {"x": 237, "y": 292}]}, "text": "\u6750"}]}, {"property": {"detectedLanguages": [{"languageCode": "ja"}]}, "boundingBox": {"vertices": [{"x": 269, "y": 274}, {"x": 332, "y": 282}, {"x": 329, "y": 304}, {"x": 266, "y": 296}]}, "symbols": [{"property": {"detectedLanguages": [{"languageCode": "ja"}]}, "boundingBox": {"vertices": [{"x": 269, "y": 274}, {"x": 317, "y": 280}, {"x": 314, "y": 302}, {"x": 266, "y": 296}]}, "text": "\u4e00"}, {"property": {"detectedLanguages": [{"languageCode": "ja"}]}, "boundingBox": {"vertices": [{"x": 317, "y": 280}, {"x": 332, "y": 282}, {"x": 329, "y": 304}, {"x": 314, "y": 302}]}, "text": "\u90e8"}]}, {"property": {"detectedLanguages": [{"languageCode": "ja"}]}, "boundingBox": {"vertices": [{"x": 334, "y": 282}, {"x": 347, "y": 284}, {"x": 344, "y": 305}, {"x": 331, "y": 304}]}, "symbols": [{"property": {"detectedLanguages": [{"languageCode": "ja"}]}, "boundingBox": {"vertices": [{"x": 334, "y": 282}, {"x": 347, "y": 284}, {"x": 344, "y": 305}, {"x": 331, "y": 304}]}, "text": "\u306b"}]}, {"property": {"detectedLanguages": [{"languageCode": "ja"}]}, "boundingBox": {"vertices": [{"x": 349, "y": 284}, {"x": 381, "y": 288}, {"x": 378, "y": 310}, {"x": 346, "y": 306}]}, "symbols": [{"property": {"detectedLanguages": [{"languageCode": "ja"}]}, "boundingBox": {"vertices": [{"x": 349, "y": 284}, {"x": 381, "y": 288}, {"x": 378, "y": 310}, {"x": 346, "y": 306}]}, "text": "\u3001"}]}, {"property": {"detectedLanguages": [{"languageCode": "ja"}]}, "boundingBox": {"vertices": [{"x": 383, "y": 288}, {"x": 420, "y": 293}, {"x": 417, "y": 314}, {"x": 380, "y": 310}]}, "symbols": [{"property": {"detectedLanguages": [{"languageCode": "ja"}]}, "boundingBox": {"vertices": [{"x": 383, "y": 288}, {"x": 404, "y": 291}, {"x": 401, "y": 312}, {"x": 380, "y": 310}]}, "text": "\u5c0f"}, {"property": {"detectedLanguages": [{"languageCode": "ja"}]}, "boundingBox": {"vertices": [{"x": 405, "y": 291}, {"x": 420, "y": 293}, {"x": 417, "y": 315}, {"x": 402, "y": 313}]}, "text": "\u9ea6"}]}, {"property": {"detectedLanguages": [{"languageCode": "ja"}]}, "boundingBox": {"vertices": [{"x": 421, "y": 293}, {"x": 426, "y": 294}, {"x": 423, "y": 315}, {"x": 418, "y": 315}]}, "symbols": [{"property": {"detectedLanguages": [{"languageCode": "ja"}]}, "boundingBox": {"vertices": [{"x": 421, "y": 293}, {"x": 426, "y": 294}, {"x": 423, "y": 315}, {"x": 418, "y": 315}]}, "text": "\u3001"}]}, {"property": {"detectedLanguages": [{"languageCode": "ja"}]}, "boundingBox": {"vertices": [{"x": 428, "y": 294}, {"x": 449, "y": 297}, {"x": 446, "y": 318}, {"x": 425, "y": 316}]}, "symbols": [{"property": {"detectedLanguages": [{"languageCode": "ja"}]}, "boundingBox": {"vertices": [{"x": 428, "y": 294}, {"x": 449, "y": 297}, {"x": 446, "y": 318}, {"x": 425, "y": 316}]}, "text": "\u8c5a"}]}, {"property": {"detectedLanguages": [{"languageCode": "ja"}]}, "boundingBox": {"vertices": [{"x": 451, "y": 297}, {"x": 469, "y": 299}, {"x": 466, "y": 321}, {"x": 448, "y": 319}]}, "symbols": [{"property": {"detectedLanguages": [{"languageCode": "ja"}]}, "boundingBox": {"vertices": [{"x": 451, "y": 297}, {"x": 469, "y": 299}, {"x": 466, "y": 321}, {"x": 448, "y": 319}]}, "text": "\u8089"}]}, {"property": {"detectedLanguages": [{"languageCode": "ja"}]}, "boundingBox": {"vertices": [{"x": 471, "y": 300}, {"x": 484, "y": 302}, {"x": 481, "y": 323}, {"x": 468, "y": 322}]}, "symbols": [{"property": {"detectedLanguages": [{"languageCode": "ja"}]}, "boundingBox": {"vertices": [{"x": 471, "y": 300}, {"x": 484, "y": 302}, {"x": 481, "y": 323}, {"x": 468, "y": 322}]}, "text": "\u3092"}]}, {"property": {"detectedLanguages": [{"languageCode": "ja"}]}, "boundingBox": {"vertices": [{"x": 486, "y": 302}, {"x": 499, "y": 304}, {"x": 496, "y": 325}, {"x": 483, "y": 324}]}, "symbols": [{"property": {"detectedLanguages": [{"languageCode": "ja"}]}, "boundingBox": {"vertices": [{"x": 486, "y": 302}, {"x": 499, "y": 304}, {"x": 496, "y": 325}, {"x": 483, "y": 324}]}, "text": "\u542b"}]}, {"property": {"detectedLanguages": [{"languageCode": "ja"}]}, "boundingBox": {"vertices": [{"x": 501, "y": 303}, {"x": 518, "y": 305}, {"x": 515, "y": 327}, {"x": 498, "y": 325}]}, "symbols": [{"property": {"detectedLanguages": [{"languageCode": "ja"}]}, "boundingBox": {"vertices": [{"x": 501, "y": 303}, {"x": 518, "y": 305}, {"x": 515, "y": 327}, {"x": 498, "y": 325}]}, "text": "\u3080"}]}, {"property": {"detectedLanguages": [{"languageCode": "ja"}]}, "boundingBox": {"vertices": [{"x": 520, "y": 306}, {"x": 522, "y": 306}, {"x": 519, "y": 328}, {"x": 517, "y": 328}]}, "symbols": [{"property": {"detectedLanguages": [{"languageCode": "ja"}], "detectedBreak": {"type": "EOL_SURE_SPACE"}}, "boundingBox": {"vertices": [{"x": 520, "y": 306}, {"x": 522, "y": 306}, {"x": 519, "y": 328}, {"x": 517, "y": 328}]}, "text": ")"}]}, {"property": {"detectedLanguages": [{"languageCode": "ja"}]}, "boundingBox": {"vertices": [{"x": 265, "y": 294}, {"x": 285, "y": 297}, {"x": 282, "y": 319}, {"x": 262, "y": 317}]}, "symbols": [{"property": {"detectedLanguages": [{"languageCode": "ja"}], "detectedBreak": {"type": "SPACE"}}, "boundingBox": {"vertices": [{"x": 265, "y": 294}, {"x": 285, "y": 297}, {"x": 282, "y": 319}, {"x": 262, "y": 317}]}, "text": "\u8b70"}]}, {"property": {"detectedLanguages": [{"languageCode": "ja"}]}, "boundingBox": {"vertices": [{"x": 301, "y": 302}, {"x": 322, "y": 305}, {"x": 319, "y": 325}, {"x": 298, "y": 322}]}, "symbols": [{"property": {"detectedLanguages": [{"languageCode": "ja"}]}, "boundingBox": {"vertices": [{"x": 301, "y": 303}, {"x": 307, "y": 304}, {"x": 305, "y": 323}, {"x": 299, "y": 322}]}, "text": "1"}, {"property": {"detectedLanguages": [{"languageCode": "ja"}], "detectedBreak": {"type": "SPACE"}}, "boundingBox": {"vertices": [{"x": 312, "y": 303}, {"x": 322, "y": 304}, {"x": 319, "y": 324}, {"x": 309, "y": 323}]}, "text": "9"}]}, {"property": {"detectedLanguages": [{"languageCode": "ja"}]}, "boundingBox": {"vertices": [{"x": 333, "y": 306}, {"x": 368, "y": 310}, {"x": 365, "y": 330}, {"x": 330, "y": 326}]}, "symbols": [{"property": {"detectedLanguages": [{"languageCode": "ja"}]}, "boundingBox": {"vertices": [{"x": 333, "y": 306}, {"x": 360, "y": 309}, {"x": 357, "y": 329}, {"x": 330, "y": 326}]}, "text": "9"}, {"property": {"detectedLanguages": [{"languageCode": "ja"}]}, "boundingBox": {"vertices": [{"x": 360, "y": 309}, {"x": 368, "y": 310}, {"x": 365, "y": 330}, {"x": 357, "y": 329}]}, "text": "6"}]}, {"property": {"detectedLanguages": [{"languageCode": "ja"}]}, "boundingBox": {"vertices": [{"x": 383, "y": 312}, {"x": 442, "y": 320}, {"x": 439, "y": 339}, {"x": 380, "y": 332}]}, "symbols": [{"property": {"detectedLanguages": [{"languageCode": "ja"}]}, "boundingBox": {"vertices": [{"x": 383, "y": 312}, {"x": 426, "y": 318}, {"x": 423, "y": 337}, {"x": 380, "y": 332}]}, "text": "\u5348"}, {"property": {"detectedLanguages": [{"languageCode": "ja"}]}, "boundingBox": {"vertices": [{"x": 427, "y": 318}, {"x": 442, "y": 320}, {"x": 439, "y": 340}, {"x": 424, "y": 338}]}, "text": "\u5f8c"}]}, {"property": {"detectedLanguages": [{"languageCode": "ja"}]}, "boundingBox": {"vertices": [{"x": 444, "y": 317}, {"x": 475, "y": 321}, {"x": 472, "y": 344}, {"x": 441, "y": 340}]}, "symbols": [{"property": {"detectedLanguages": [{"languageCode": "ja"}]}, "boundingBox": {"vertices": [{"x": 444, "y": 317}, {"x": 467, "y": 320}, {"x": 464, "y": 343}, {"x": 441, "y": 340}]}, "text": "4"}, {"property": {"detectedLanguages": [{"languageCode": "ja"}]}, "boundingBox": {"vertices": [{"x": 468, "y": 320}, {"x": 475, "y": 321}, {"x": 472, "y": 344}, {"x": 465, "y": 343}]}, "text": "8"}]}, {"property": {"detectedLanguages": [{"languageCode": "ja"}]}, "boundingBox": {"vertices": [{"x": 477, "y": 321}, {"x": 483, "y": 322}, {"x": 480, "y": 345}, {"x": 474, "y": 344}]}, "symbols": [{"property": {"detectedLanguages": [{"languageCode": "ja"}], "detectedBreak": {"type": "EOL_SURE_SPACE"}}, "boundingBox": {"vertices": [{"x": 477, "y": 321}, {"x": 483, "y": 322}, {"x": 480, "y": 345}, {"x": 474, "y": 344}]}, "text": "\u6642"}]}, {"property": {"detectedLanguages": [{"languageCode": "ja"}]}, "boundingBox": {"vertices": [{"x": 204, "y": 306}, {"x": 248, "y": 312}, {"x": 245, "y": 332}, {"x": 201, "y": 327}]}, "symbols": [{"property": {"detectedLanguages": [{"languageCode": "ja"}]}, "boundingBox": {"vertices": [{"x": 204, "y": 306}, {"x": 230, "y": 309}, {"x": 227, "y": 330}, {"x": 201, "y": 327}]}, "text": "\u4fdd"}, {"property": {"detectedLanguages": [{"languageCode": "ja"}]}, "boundingBox": {"vertices": [{"x": 231, "y": 309}, {"x": 248, "y": 311}, {"x": 245, "y": 332}, {"x": 228, "y": 330}]}, "text": "\u5b58"}]}, {"property": {"detectedLanguages": [{"languageCode": "ja"}]}, "boundingBox": {"vertices": [{"x": 250, "y": 312}, {"x": 285, "y": 316}, {"x": 282, "y": 337}, {"x": 247, "y": 333}]}, "symbols": [{"property": {"detectedLanguages": [{"languageCode": "ja"}]}, "boundingBox": {"vertices": [{"x": 250, "y": 312}, {"x": 259, "y": 313}, {"x": 256, "y": 334}, {"x": 247, "y": 333}]}, "text": "\u65b9"}, {"property": {"detectedLanguages": [{"languageCode": "ja"}]}, "boundingBox": {"vertices": [{"x": 259, "y": 313}, {"x": 284, "y": 316}, {"x": 281, "y": 337}, {"x": 256, "y": 334}]}, "text": "\u6cd5"}]}, {"property": {"detectedLanguages": [{"languageCode": "ja"}]}, "boundingBox": {"vertices": [{"x": 286, "y": 317}, {"x": 328, "y": 322}, {"x": 325, "y": 343}, {"x": 283, "y": 338}]}, "symbols": [{"property": {"detectedLanguages": [{"languageCode": "ja"}]}, "boundingBox": {"vertices": [{"x": 286, "y": 317}, {"x": 328, "y": 322}, {"x": 325, "y": 343}, {"x": 283, "y": 338}]}, "text": "\u5c04"}]}, {"property": {"detectedLanguages": [{"languageCode": "ja"}]}, "boundingBox": {"vertices": [{"x": 330, "y": 322}, {"x": 365, "y": 326}, {"x": 362, "y": 347}, {"x": 327, "y": 343}]}, "symbols": [{"property": {"detectedLanguages": [{"languageCode": "ja"}]}, "boundingBox": {"vertices": [{"x": 330, "y": 322}, {"x": 335, "y": 323}, {"x": 332, "y": 343}, {"x": 327, "y": 343}]}, "text": "\u65e5"}, {"property": {"detectedLanguages": [{"languageCode": "ja"}]}, "boundingBox": {"vertices": [{"x": 336, "y": 323}, {"x": 365, "y": 327}, {"x": 362, "y": 348}, {"x": 333, "y": 344}]}, "text": "\u5149"}]}, {"property": {"detectedLanguages": [{"languageCode": "ja"}]}, "boundingBox": {"vertices": [{"x": 367, "y": 327}, {"x": 398, "y": 331}, {"x": 395, "y": 352}, {"x": 364, "y": 348}]}, "symbols": [{"property": {"detectedLanguages": [{"languageCode": "ja"}]}, "boundingBox": {"vertices": [{"x": 367, "y": 327}, {"x": 379, "y": 329}, {"x": 376, "y": 349}, {"x": 364, "y": 348}]}, "text": "\u53ca"}, {"property": {"detectedLanguages": [{"languageCode": "ja"}]}, "boundingBox": {"vertices": [{"x": 380, "y": 329}, {"x": 398, "y": 331}, {"x": 395, "y": 352}, {"x": 377, "y": 350}]}, "text": "\u3073"}]}, {"property": {"detectedLanguages": [{"languageCode": "ja"}]}, "boundingBox": {"vertices": [{"x": 399, "y": 331}, {"x": 444, "y": 337}, {"x": 441, "y": 358}, {"x": 396, "y": 352}]}, "symbols": [{"property": {"detectedLanguages": [{"languageCode": "ja"}]}, "boundingBox": {"vertices": [{"x": 399, "y": 331}, {"x": 444, "y": 337}, {"x": 441, "y": 358}, {"x": 396, "y": 352}]}, "text": "\u4e8b"}]}, {"property": {"detectedLanguages": [{"languageCode": "ja"}]}, "boundingBox": {"vertices": [{"x": 443, "y": 340}, {"x": 457, "y": 342}, {"x": 455, "y": 357}, {"x": 441, "y": 355}]}, "symbols": [{"property": {"detectedLanguages": [{"languageCode": "ja"}]}, "boundingBox": {"vertices": [{"x": 443, "y": 340}, {"x": 457, "y": 342}, {"x": 455, "y": 357}, {"x": 441, "y": 355}]}, "text": "\u6e29"}]}, {"property": {"detectedLanguages": [{"languageCode": "ja"}]}, "boundingBox": {"vertices": [{"x": 461, "y": 343}, {"x": 472, "y": 344}, {"x": 470, "y": 358}, {"x": 459, "y": 357}]}, "symbols": [{"property": {"detectedLanguages": [{"languageCode": "ja"}]}, "boundingBox": {"vertices": [{"x": 461, "y": 343}, {"x": 472, "y": 344}, {"x": 470, "y": 358}, {"x": 459, "y": 357}]}, "text": "\u3092"}]}, {"property": {"detectedLanguages": [{"languageCode": "ja"}]}, "boundingBox": {"vertices": [{"x": 476, "y": 341}, {"x": 507, "y": 345}, {"x": 504, "y": 363}, {"x": 474, "y": 359}]}, "symbols": [{"property": {"detectedLanguages": [{"languageCode": "ja"}]}, "boundingBox": {"vertices": [{"x": 476, "y": 341}, {"x": 499, "y": 344}, {"x": 497, "y": 362}, {"x": 474, "y": 359}]}, "text": "\u907f"}, {"property": {"detectedLanguages": [{"languageCode": "ja"}]}, "boundingBox": {"vertices": [{"x": 500, "y": 344}, {"x": 507, "y": 345}, {"x": 505, "y": 363}, {"x": 498, "y": 362}]}, "text": "\u3051"}]}, {"property": {"detectedLanguages": [{"languageCode": "ja"}]}, "boundingBox": {"vertices": [{"x": 508, "y": 345}, {"x": 531, "y": 348}, {"x": 528, "y": 369}, {"x": 505, "y": 366}]}, "symbols": [{"property": {"detectedLanguages": [{"languageCode": "ja"}]}, "boundingBox": {"vertices": [{"x": 508, "y": 345}, {"x": 531, "y": 348}, {"x": 528, "y": 369}, {"x": 505, "y": 366}]}, "text": "\u3066"}]}, {"property": {"detectedLanguages": [{"languageCode": "ja"}]}, "boundingBox": {"vertices": [{"x": 533, "y": 348}, {"x": 572, "y": 353}, {"x": 569, "y": 375}, {"x": 530, "y": 370}]}, "symbols": [{"property": {"detectedLanguages": [{"languageCode": "ja"}]}, "boundingBox": {"vertices": [{"x": 533, "y": 348}, {"x": 550, "y": 350}, {"x": 547, "y": 371}, {"x": 530, "y": 369}]}, "text": "\u4e0b"}, {"property": {"detectedLanguages": [{"languageCode": "ja"}]}, "boundingBox": {"vertices": [{"x": 551, "y": 351}, {"x": 561, "y": 352}, {"x": 558, "y": 373}, {"x": 548, "y": 372}]}, "text": "\u3055"}, {"property": {"detectedLanguages": [{"languageCode": "ja"}], "detectedBreak": {"type": "EOL_SURE_SPACE"}}, "boundingBox": {"vertices": [{"x": 562, "y": 352}, {"x": 572, "y": 353}, {"x": 569, "y": 374}, {"x": 559, "y": 373}]}, "text": "\u3044"}]}]}], "blockType": "TEXT"}, {"boundingBox": {"vertices": [{"x": 564, "y": 337}, {"x": 593, "y": 341}, {"x": 590, "y": 357}, {"x": 562, "y": 353}]}, "paragraphs": [{"boundingBox": {"vertices": [{"x": 564, "y": 337}, {"x": 593, "y": 341}, {"x": 590, "y": 357}, {"x": 562, "y": 353}]}, "words": [{"boundingBox": {"vertices": [{"x": 564, "y": 337}, {"x": 593, "y": 341}, {"x": 590, "y": 357}, {"x": 562, "y": 353}]}, "symbols": [{"boundingBox": {"vertices": [{"x": 564, "y": 337}, {"x": 575, "y": 339}, {"x": 572, "y": 354}, {"x": 562, "y": 353}]}, "text": "P"}, {"boundingBox": {"vertices": [{"x": 576, "y": 339}, {"x": 578, "y": 339}, {"x": 576, "y": 355}, {"x": 574, "y": 355}]}, "text": "J"}, {"boundingBox": {"vertices": [{"x": 579, "y": 339}, {"x": 585, "y": 340}, {"x": 582, "y": 356}, {"x": 577, "y": 355}]}, "text": "2"}, {"property": {"detectedBreak": {"type": "EOL_SURE_SPACE"}}, "boundingBox": {"vertices": [{"x": 586, "y": 340}, {"x": 593, "y": 341}, {"x": 590, "y": 357}, {"x": 584, "y": 356}]}, "text": "3"}]}]}], "blockType": "TEXT"}, {"boundingBox": {"vertices": [{"x": 496, "y": 362}, {"x": 583, "y": 372}, {"x": 581, "y": 391}, {"x": 494, "y": 381}]}, "paragraphs": [{"boundingBox": {"vertices": [{"x": 496, "y": 362}, {"x": 583, "y": 372}, {"x": 581, "y": 391}, {"x": 494, "y": 381}]}, "words": [{"boundingBox": {"vertices": [{"x": 496, "y": 362}, {"x": 583, "y": 372}, {"x": 581, "y": 391}, {"x": 494, "y": 381}]}, "symbols": [{"boundingBox": {"vertices": [{"x": 496, "y": 363}, {"x": 503, "y": 364}, {"x": 501, "y": 382}, {"x": 494, "y": 381}]}, "text": "0"}, {"boundingBox": {"vertices": [{"x": 504, "y": 364}, {"x": 510, "y": 365}, {"x": 508, "y": 383}, {"x": 502, "y": 382}]}, "text": "1"}, {"boundingBox": {"vertices": [{"x": 511, "y": 364}, {"x": 517, "y": 365}, {"x": 515, "y": 383}, {"x": 509, "y": 382}]}, "text": "2"}, {"boundingBox": {"vertices": [{"x": 518, "y": 365}, {"x": 524, "y": 366}, {"x": 522, "y": 384}, {"x": 516, "y": 383}]}, "text": "0"}, {"boundingBox": {"vertices": [{"x": 525, "y": 366}, {"x": 535, "y": 367}, {"x": 533, "y": 385}, {"x": 523, "y": 384}]}, "text": "-"}, {"boundingBox": {"vertices": [{"x": 536, "y": 368}, {"x": 542, "y": 369}, {"x": 540, "y": 387}, {"x": 534, "y": 386}]}, "text": "6"}, {"boundingBox": {"vertices": [{"x": 543, "y": 368}, {"x": 549, "y": 369}, {"x": 547, "y": 387}, {"x": 541, "y": 386}]}, "text": "3"}, {"boundingBox": {"vertices": [{"x": 550, "y": 369}, {"x": 559, "y": 370}, {"x": 557, "y": 388}, {"x": 548, "y": 387}]}, "text": "4"}, {"boundingBox": {"vertices": [{"x": 560, "y": 370}, {"x": 566, "y": 371}, {"x": 564, "y": 389}, {"x": 558, "y": 388}]}, "text": "0"}, {"boundingBox": {"vertices": [{"x": 566, "y": 371}, {"x": 572, "y": 372}, {"x": 570, "y": 390}, {"x": 564, "y": 389}]}, "text": "5"}, {"property": {"detectedBreak": {"type": "EOL_SURE_SPACE"}}, "boundingBox": {"vertices": [{"x": 573, "y": 372}, {"x": 583, "y": 373}, {"x": 581, "y": 391}, {"x": 571, "y": 390}]}, "text": "8"}]}]}], "blockType": "TEXT"}, {"boundingBox": {"vertices": [{"x": 257, "y": 349}, {"x": 407, "y": 369}, {"x": 404, "y": 389}, {"x": 254, "y": 369}]}, "paragraphs": [{"boundingBox": {"vertices": [{"x": 257, "y": 349}, {"x": 407, "y": 369}, {"x": 404, "y": 389}, {"x": 254, "y": 369}]}, "words": [{"boundingBox": {"vertices": [{"x": 257, "y": 350}, {"x": 349, "y": 362}, {"x": 347, "y": 381}, {"x": 254, "y": 369}]}, "symbols": [{"boundingBox": {"vertices": [{"x": 257, "y": 350}, {"x": 337, "y": 361}, {"x": 335, "y": 380}, {"x": 254, "y": 369}]}, "text": "1"}, {"property": {"detectedBreak": {"type": "SPACE"}}, "boundingBox": {"vertices": [{"x": 339, "y": 361}, {"x": 349, "y": 362}, {"x": 346, "y": 381}, {"x": 336, "y": 380}]}, "text": "1"}]}, {"boundingBox": {"vertices": [{"x": 354, "y": 362}, {"x": 407, "y": 369}, {"x": 404, "y": 389}, {"x": 351, "y": 382}]}, "symbols": [{"boundingBox": {"vertices": [{"x": 354, "y": 363}, {"x": 366, "y": 365}, {"x": 363, "y": 383}, {"x": 351, "y": 382}]}, "text": "2"}, {"boundingBox": {"vertices": [{"x": 367, "y": 364}, {"x": 384, "y": 366}, {"x": 381, "y": 385}, {"x": 364, "y": 383}]}, "text": "-"}, {"boundingBox": {"vertices": [{"x": 384, "y": 367}, {"x": 393, "y": 368}, {"x": 390, "y": 387}, {"x": 381, "y": 386}]}, "text": "4"}, {"property": {"detectedBreak": {"type": "EOL_SURE_SPACE"}}, "boundingBox": {"vertices": [{"x": 393, "y": 368}, {"x": 406, "y": 370}, {"x": 403, "y": 389}, {"x": 390, "y": 387}]}, "text": "8"}]}]}], "blockType": "TEXT"}, {"property": {"detectedLanguages": [{"languageCode": "zh", "confidence": 0.58}, {"languageCode": "en", "confidence": 0.42}]}, "boundingBox": {"vertices": [{"x": 195, "y": 365}, {"x": 427, "y": 397}, {"x": 421, "y": 439}, {"x": 189, "y": 407}]}, "paragraphs": [{"property": {"detectedLanguages": [{"languageCode": "zh", "confidence": 0.58}, {"languageCode": "en", "confidence": 0.42}]}, "boundingBox": {"vertices": [{"x": 195, "y": 365}, {"x": 427, "y": 397}, {"x": 421, "y": 439}, {"x": 189, "y": 407}]}, "words": [{"property": {"detectedLanguages": [{"languageCode": "en"}]}, "boundingBox": {"vertices": [{"x": 195, "y": 367}, {"x": 217, "y": 370}, {"x": 214, "y": 392}, {"x": 192, "y": 389}]}, "symbols": [{"property": {"detectedLanguages": [{"languageCode": "en"}], "detectedBreak": {"type": "SPACE"}}, "boundingBox": {"vertices": [{"x": 195, "y": 367}, {"x": 217, "y": 370}, {"x": 214, "y": 392}, {"x": 192, "y": 389}]}, "text": "1"}]}, {"property": {"detectedLanguages": [{"languageCode": "en"}]}, "boundingBox": {"vertices": [{"x": 219, "y": 370}, {"x": 228, "y": 371}, {"x": 225, "y": 393}, {"x": 216, "y": 392}]}, "symbols": [{"property": {"detectedLanguages": [{"languageCode": "en"}], "detectedBreak": {"type": "SPACE"}}, "boundingBox": {"vertices": [{"x": 219, "y": 370}, {"x": 228, "y": 371}, {"x": 225, "y": 393}, {"x": 216, "y": 392}]}, "text": "2"}]}, {"property": {"detectedLanguages": [{"languageCode": "en"}]}, "boundingBox": {"vertices": [{"x": 272, "y": 378}, {"x": 281, "y": 379}, {"x": 278, "y": 401}, {"x": 269, "y": 400}]}, "symbols": [{"property": {"detectedLanguages": [{"languageCode": "en"}], "detectedBreak": {"type": "SPACE"}}, "boundingBox": {"vertices": [{"x": 272, "y": 378}, {"x": 281, "y": 379}, {"x": 278, "y": 401}, {"x": 269, "y": 400}]}, "text": "U"}]}, {"property": {"detectedLanguages": [{"languageCode": "en"}]}, "boundingBox": {"vertices": [{"x": 286, "y": 381}, {"x": 348, "y": 389}, {"x": 346, "y": 409}, {"x": 283, "y": 401}]}, "symbols": [{"property": {"detectedLanguages": [{"languageCode": "en"}]}, "boundingBox": {"vertices": [{"x": 286, "y": 381}, {"x": 319, "y": 385}, {"x": 316, "y": 405}, {"x": 283, "y": 401}]}, "text": "P"}, {"property": {"detectedLanguages": [{"languageCode": "en"}]}, "boundingBox": {"vertices": [{"x": 323, "y": 390}, {"x": 328, "y": 391}, {"x": 326, "y": 404}, {"x": 321, "y": 403}]}, "text": "A"}, {"property": {"detectedLanguages": [{"languageCode": "en"}], "detectedBreak": {"type": "SPACE"}}, "boundingBox": {"vertices": [{"x": 337, "y": 390}, {"x": 348, "y": 391}, {"x": 346, "y": 407}, {"x": 335, "y": 406}]}, "text": "9"}]}, {"property": {"detectedLanguages": [{"languageCode": "en"}]}, "boundingBox": {"vertices": [{"x": 354, "y": 392}, {"x": 391, "y": 397}, {"x": 388, "y": 416}, {"x": 351, "y": 411}]}, "symbols": [{"property": {"detectedLanguages": [{"languageCode": "en"}]}, "boundingBox": {"vertices": [{"x": 354, "y": 393}, {"x": 364, "y": 394}, {"x": 362, "y": 412}, {"x": 352, "y": 411}]}, "text": "2"}, {"property": {"detectedLanguages": [{"languageCode": "en"}]}, "boundingBox": {"vertices": [{"x": 365, "y": 394}, {"x": 376, "y": 395}, {"x": 373, "y": 413}, {"x": 363, "y": 412}]}, "text": "k"}, {"property": {"detectedLanguages": [{"languageCode": "en"}]}, "boundingBox": {"vertices": [{"x": 377, "y": 396}, {"x": 383, "y": 397}, {"x": 381, "y": 415}, {"x": 375, "y": 414}]}, "text": "c"}, {"property": {"detectedLanguages": [{"languageCode": "en"}]}, "boundingBox": {"vertices": [{"x": 384, "y": 397}, {"x": 387, "y": 397}, {"x": 385, "y": 415}, {"x": 382, "y": 415}]}, "text": "a"}, {"property": {"detectedLanguages": [{"languageCode": "en"}], "detectedBreak": {"type": "EOL_SURE_SPACE"}}, "boundingBox": {"vertices": [{"x": 388, "y": 397}, {"x": 391, "y": 397}, {"x": 389, "y": 415}, {"x": 386, "y": 415}]}, "text": "l"}]}, {"property": {"detectedLanguages": [{"languageCode": "zh"}]}, "boundingBox": {"vertices": [{"x": 201, "y": 388}, {"x": 221, "y": 391}, {"x": 218, "y": 410}, {"x": 198, "y": 407}]}, "symbols": [{"property": {"detectedLanguages": [{"languageCode": "zh"}]}, "boundingBox": {"vertices": [{"x": 201, "y": 388}, {"x": 221, "y": 391}, {"x": 218, "y": 410}, {"x": 198, "y": 407}]}, "text": "\u70ad"}]}, {"property": {"detectedLanguages": [{"languageCode": "zh"}]}, "boundingBox": {"vertices": [{"x": 223, "y": 391}, {"x": 249, "y": 395}, {"x": 246, "y": 414}, {"x": 220, "y": 410}]}, "symbols": [{"property": {"detectedLanguages": [{"languageCode": "zh"}]}, "boundingBox": {"vertices": [{"x": 223, "y": 391}, {"x": 231, "y": 392}, {"x": 228, "y": 411}, {"x": 220, "y": 410}]}, "text": "\u6c34"}, {"property": {"detectedLanguages": [{"languageCode": "zh"}]}, "boundingBox": {"vertices": [{"x": 232, "y": 392}, {"x": 249, "y": 394}, {"x": 246, "y": 413}, {"x": 229, "y": 411}]}, "text": "\u5316"}]}, {"property": {"detectedLanguages": [{"languageCode": "zh"}]}, "boundingBox": {"vertices": [{"x": 250, "y": 395}, {"x": 265, "y": 397}, {"x": 262, "y": 416}, {"x": 247, "y": 414}]}, "symbols": [{"property": {"detectedLanguages": [{"languageCode": "zh"}]}, "boundingBox": {"vertices": [{"x": 250, "y": 395}, {"x": 265, "y": 397}, {"x": 262, "y": 416}, {"x": 247, "y": 414}]}, "text": "\u7269"}]}, {"property": {"detectedLanguages": [{"languageCode": "zh"}]}, "boundingBox": {"vertices": [{"x": 267, "y": 397}, {"x": 325, "y": 405}, {"x": 323, "y": 425}, {"x": 264, "y": 417}]}, "symbols": [{"property": {"detectedLanguages": [{"languageCode": "zh"}]}, "boundingBox": {"vertices": [{"x": 267, "y": 397}, {"x": 279, "y": 399}, {"x": 276, "y": 418}, {"x": 264, "y": 416}]}, "text": "3"}, {"property": {"detectedLanguages": [{"languageCode": "zh"}]}, "boundingBox": {"vertices": [{"x": 280, "y": 399}, {"x": 297, "y": 401}, {"x": 294, "y": 420}, {"x": 277, "y": 418}]}, "text": "7"}, {"property": {"detectedLanguages": [{"languageCode": "zh"}]}, "boundingBox": {"vertices": [{"x": 298, "y": 402}, {"x": 300, "y": 402}, {"x": 297, "y": 421}, {"x": 295, "y": 421}]}, "text": "."}, {"property": {"detectedLanguages": [{"languageCode": "zh"}]}, "boundingBox": {"vertices": [{"x": 301, "y": 402}, {"x": 314, "y": 404}, {"x": 311, "y": 423}, {"x": 298, "y": 421}]}, "text": "4"}, {"property": {"detectedLanguages": [{"languageCode": "zh"}], "detectedBreak": {"type": "SPACE"}}, "boundingBox": {"vertices": [{"x": 315, "y": 404}, {"x": 325, "y": 405}, {"x": 322, "y": 424}, {"x": 312, "y": 423}]}, "text": "g"}]}, {"property": {"detectedLanguages": [{"languageCode": "zh"}]}, "boundingBox": {"vertices": [{"x": 332, "y": 411}, {"x": 357, "y": 415}, {"x": 355, "y": 426}, {"x": 330, "y": 423}]}, "symbols": [{"property": {"detectedLanguages": [{"languageCode": "zh"}]}, "boundingBox": {"vertices": [{"x": 332, "y": 411}, {"x": 343, "y": 413}, {"x": 341, "y": 423}, {"x": 330, "y": 422}]}, "text": "N"}, {"property": {"detectedLanguages": [{"languageCode": "zh"}], "detectedBreak": {"type": "SPACE"}}, "boundingBox": {"vertices": [{"x": 349, "y": 415}, {"x": 357, "y": 416}, {"x": 355, "y": 426}, {"x": 348, "y": 425}]}, "text": "a"}]}, {"property": {"detectedLanguages": [{"languageCode": "zh"}]}, "boundingBox": {"vertices": [{"x": 366, "y": 414}, {"x": 385, "y": 417}, {"x": 383, "y": 431}, {"x": 364, "y": 428}]}, "symbols": [{"property": {"detectedLanguages": [{"languageCode": "zh"}]}, "boundingBox": {"vertices": [{"x": 366, "y": 414}, {"x": 373, "y": 415}, {"x": 371, "y": 429}, {"x": 364, "y": 428}]}, "text": "2"}, {"property": {"detectedLanguages": [{"languageCode": "zh"}], "detectedBreak": {"type": "SPACE"}}, "boundingBox": {"vertices": [{"x": 383, "y": 418}, {"x": 385, "y": 418}, {"x": 385, "y": 419}, {"x": 383, "y": 419}]}, "text": "1"}]}, {"property": {"detectedLanguages": [{"languageCode": "zh"}]}, "boundingBox": {"vertices": [{"x": 398, "y": 418}, {"x": 424, "y": 422}, {"x": 422, "y": 437}, {"x": 396, "y": 433}]}, "symbols": [{"property": {"detectedLanguages": [{"languageCode": "zh"}]}, "boundingBox": {"vertices": [{"x": 398, "y": 418}, {"x": 406, "y": 419}, {"x": 404, "y": 432}, {"x": 396, "y": 431}]}, "text": "8"}, {"property": {"detectedLanguages": [{"languageCode": "zh"}], "detectedBreak": {"type": "EOL_SURE_SPACE"}}, "boundingBox": {"vertices": [{"x": 410, "y": 424}, {"x": 423, "y": 426}, {"x": 421, "y": 437}, {"x": 408, "y": 435}]}, "text": "g"}]}]}], "blockType": "TEXT"}, {"property": {"detectedLanguages": [{"languageCode": "en", "confidence": 1}]}, "boundingBox": {"vertices": [{"x": 451, "y": 402}, {"x": 581, "y": 420}, {"x": 578, "y": 441}, {"x": 448, "y": 424}]}, "paragraphs": [{"property": {"detectedLanguages": [{"languageCode": "en", "confidence": 1}]}, "boundingBox": {"vertices": [{"x": 451, "y": 402}, {"x": 581, "y": 420}, {"x": 578, "y": 441}, {"x": 448, "y": 424}]}, "words": [{"property": {"detectedLanguages": [{"languageCode": "en"}]}, "boundingBox": {"vertices": [{"x": 451, "y": 402}, {"x": 498, "y": 408}, {"x": 495, "y": 430}, {"x": 448, "y": 424}]}, "symbols": [{"property": {"detectedLanguages": [{"languageCode": "en"}]}, "boundingBox": {"vertices": [{"x": 451, "y": 402}, {"x": 487, "y": 407}, {"x": 484, "y": 429}, {"x": 448, "y": 424}]}, "text": "8"}, {"property": {"detectedLanguages": [{"languageCode": "en"}], "detectedBreak": {"type": "SPACE"}}, "boundingBox": {"vertices": [{"x": 487, "y": 407}, {"x": 497, "y": 408}, {"x": 494, "y": 430}, {"x": 484, "y": 429}]}, "text": "g"}]}, {"property": {"detectedLanguages": [{"languageCode": "en"}]}, "boundingBox": {"vertices": [{"x": 503, "y": 411}, {"x": 548, "y": 417}, {"x": 545, "y": 434}, {"x": 501, "y": 428}]}, "symbols": [{"property": {"detectedLanguages": [{"languageCode": "en"}]}, "boundingBox": {"vertices": [{"x": 503, "y": 411}, {"x": 535, "y": 415}, {"x": 532, "y": 432}, {"x": 501, "y": 428}]}, "text": "M"}, {"property": {"detectedLanguages": [{"languageCode": "en"}], "detectedBreak": {"type": "SPACE"}}, "boundingBox": {"vertices": [{"x": 538, "y": 415}, {"x": 548, "y": 416}, {"x": 546, "y": 432}, {"x": 536, "y": 431}]}, "text": "2"}]}, {"property": {"detectedLanguages": [{"languageCode": "en"}]}, "boundingBox": {"vertices": [{"x": 560, "y": 419}, {"x": 580, "y": 422}, {"x": 577, "y": 440}, {"x": 558, "y": 437}]}, "symbols": [{"property": {"detectedLanguages": [{"languageCode": "en"}]}, "boundingBox": {"vertices": [{"x": 560, "y": 419}, {"x": 569, "y": 420}, {"x": 567, "y": 436}, {"x": 558, "y": 435}]}, "text": "6"}, {"property": {"detectedLanguages": [{"languageCode": "en"}], "detectedBreak": {"type": "EOL_SURE_SPACE"}}, "boundingBox": {"vertices": [{"x": 571, "y": 424}, {"x": 580, "y": 425}, {"x": 578, "y": 440}, {"x": 569, "y": 439}]}, "text": "8"}]}]}], "blockType": "TEXT"}]}], "text": "20447 80301443\n\u540d\u79f0\u304a\u306b\u308a\nY14\n\u30d9\u30fc\u30b3\u30f3 \u305f\u307e\u3054\n\u3048\u3054\u307e\u5165\u308a\u30d9\u30fc\u30b3\u30f3\u63d0\u304d\u3001 \u3001DH\u79c1\nA (7\n\u7b49 \u30b7\u30f3\u3001\u304f\u3093\u591c\u767a\u8272\u5229(\u78bc\u4fee Na)\n\u6750\u4e00\u90e8\u306b\u3001\u5c0f\u9ea6\u3001\u8c5a\u8089\u3092\u542b\u3080)\n\u8b70 19 96\u5348\u5f8c48\u6642\n\u4fdd\u5b58\u65b9\u6cd5\u5c04\u65e5\u5149\u53ca\u3073\u4e8b\u6e29\u3092\u907f\u3051\u3066\u4e0b\u3055\u3044\nPJ23\n0120-634058\n11 2-48\n1 2 U PA9 2kcal\n\u70ad\u6c34\u5316\u726937.4g Na 21 8g\n8g M2 68\n"}}]}